{
  "uuid": "BWVyKUJt85uRly8W",
  "group": "other",
  "name": "Draining Presence Aura Immunity",
  "labels": [
    "aura"
  ],
  "source": [],
  "isActive": true,
  "baseRules": [],
  "complexRules": [
    {
      "type": "complex",
      "triggerType": "saving-throw",
      "extend": null,
      "range": null,
      "values": [
        {
          "conditions": [],
          "effects": [],
          "immunities": [
            "draining-presence"
          ],
          "duration": {
            "expiry": "round-start",
            "sustained": false,
            "unit": "hours",
            "value": 24
          }
        }
      ],
      "target": "ImmunitySelfEffect",
      "predicate": [
        {
          "or": [
            "outcome:success",
            "outcome:criticalSuccess"
          ]
        },
        "item:slug:draining-presence"
      ]
    }
  ]
}